csnlp/__init__.py
csnlp/core/__init__.py
csnlp/core/cache.py
csnlp/core/data.py
csnlp/core/debug.py
csnlp/core/derivatives.py
csnlp/core/scaling.py
csnlp/core/solutions.py
csnlp/multistart/__init__.py
csnlp/multistart/multistart_nlp.py
csnlp/multistart/startpoints.py
csnlp/nlps/__init__.py
csnlp/nlps/constraints.py
csnlp/nlps/nlp.py
csnlp/nlps/objective.py
csnlp/nlps/parameters.py
csnlp/nlps/variables.py
csnlp/util/__init__.py
csnlp/util/docs.py
csnlp/util/io.py
csnlp/util/math.py
csnlp/wrappers/__init__.py
csnlp/wrappers/scaling.py
csnlp/wrappers/sensitivity.py
csnlp/wrappers/wrapper.py
csnlp/wrappers/mpc/__init__.py
csnlp/wrappers/mpc/mpc.py
csnlp/wrappers/mpc/multi_scenario_mpc.py
csnlp/wrappers/mpc/pwa_mpc.py
csnlp/wrappers/mpc/scenario_based_mpc.py
csnlp-1.6.8.dist-info/licenses/LICENSE
csnlp-1.6.8.dist-info/METADATA
csnlp-1.6.8.dist-info/WHEEL
csnlp-1.6.8.dist-info/top_level.txt
csnlp-1.6.8.dist-info/RECORD
