Metadata-Version: 2.4
Name: csnlp
Version: 1.6.8
Summary: Nonlinear Progamming with CasADi
Author-email: Filippo Airaldi <filippoairaldi@gmail.com>
License-Expression: MIT
Project-URL: Homepage, https://github.com/FilippoAiraldi/casadi-nlp
Project-URL: Bug Tracker, https://github.com/FilippoAiraldi/casadi-nlp/issues
Keywords: nonlinear-optimization,casadi,sensitivity-analysis
Classifier: Programming Language :: Python
Classifier: Programming Language :: Python :: 3 :: Only
Classifier: Programming Language :: Python :: 3.9
Classifier: Programming Language :: Python :: 3.10
Classifier: Programming Language :: Python :: 3.11
Classifier: Programming Language :: Python :: 3.12
Classifier: Programming Language :: Python :: 3.13
Classifier: Operating System :: OS Independent
Classifier: Intended Audience :: Science/Research
Classifier: Topic :: Scientific/Engineering :: Mathematics
Classifier: Topic :: Scientific/Engineering :: Artificial Intelligence
Requires-Python: >=3.9
License-File: LICENSE
Requires-Dist: numpy<2.0.0,>=1.21.6; python_version <= "3.9"
Requires-Dist: casadi>=3.6.0
Requires-Dist: joblib>=1.4.0
Requires-Dist: typing_extensions; python_version <= "3.10"
Provides-Extra: all
Requires-Dist: matplotlib>=3.6.2; extra == "all"
Requires-Dist: tikzplotlib>=0.10.1; extra == "all"
Dynamic: license-file
